toppingmaker/__init__.py
toppingmaker/exportsettings.py
toppingmaker/projecttopping.py
toppingmaker/target.py
toppingmaker/utils.py
toppingmaker-1.6.0.dist-info/LICENSE
toppingmaker-1.6.0.dist-info/METADATA
toppingmaker-1.6.0.dist-info/WHEEL
toppingmaker-1.6.0.dist-info/top_level.txt
toppingmaker-1.6.0.dist-info/RECORD
