Metadata-Version: 2.1
Name: toppingmaker
Version: 1.6.0
Summary: Package to create parameterized QGIS projects and dump it into a YAML structure.
Home-page: https://github.com/opengisch/toppingmaker
Author: Dave Signer
Author-email: david@opengis.ch
Classifier: Topic :: Scientific/Engineering :: GIS
Classifier: License :: OSI Approved :: GNU General Public License v2 or later (GPLv2+)
Classifier: Programming Language :: Python :: 3
Classifier: License :: OSI Approved :: MIT License
Classifier: Operating System :: OS Independent
Requires-Python: >=3.6
License-File: LICENSE
